visualizer.py
visualizer-0.0.10.dist-info/LICENSE
visualizer-0.0.10.dist-info/METADATA
visualizer-0.0.10.dist-info/WHEEL
visualizer-0.0.10.dist-info/top_level.txt
visualizer-0.0.10.dist-info/RECORD
