Metadata-Version: 2.1
Name: visualizer
Version: 0.0.10
Summary: Automate the process of visualization
Home-page: https://github.com/MosaabMuhammed/visualizer
Author: Mosaab Muhammad
Author-email: mosaabmuhammed@outlook.com
License: MIT
Platform: UNKNOWN
Classifier: Programming Language :: Python :: 3
Classifier: License :: OSI Approved :: MIT License
Classifier: Operating System :: OS Independent
Requires-Python: >=3.6
